{
"meta":{"test_sets":[],"test_metrics":[],"learn_metrics":[{"best_value":"Min","name":"Logloss"}],"launch_mode":"Train","parameters":"","iteration_count":250,"learn_sets":["learn"],"name":"experiment"},
"iterations":[
{"learn":[0.6911952359],"iteration":0,"passed_time":0.01144547347,"remaining_time":2.849922895},
{"learn":[0.6893582553],"iteration":1,"passed_time":0.01448046707,"remaining_time":1.795577917},
{"learn":[0.6876293284],"iteration":2,"passed_time":0.01720903044,"remaining_time":1.416876839},
{"learn":[0.6860023158],"iteration":3,"passed_time":0.01986706647,"remaining_time":1.221824588},
{"learn":[0.6844710098],"iteration":4,"passed_time":0.0224634717,"remaining_time":1.100710113},
{"learn":[0.6832113386],"iteration":5,"passed_time":0.0250948182,"remaining_time":1.020522607},
{"learn":[0.6819968263],"iteration":6,"passed_time":0.0277431693,"remaining_time":0.9630843056},
{"learn":[0.6806906321],"iteration":7,"passed_time":0.03036559256,"remaining_time":0.9185591749},
{"learn":[0.6796311741],"iteration":8,"passed_time":0.0330862416,"remaining_time":0.8859760252},
{"learn":[0.6788159283],"iteration":9,"passed_time":0.03572344116,"remaining_time":0.8573625879},
{"learn":[0.6780319934],"iteration":10,"passed_time":0.03839328019,"remaining_time":0.8341812697},
{"learn":[0.677102691],"iteration":11,"passed_time":0.04100914549,"remaining_time":0.8133480523},
{"learn":[0.6763748977],"iteration":12,"passed_time":0.04359640699,"remaining_time":0.7947960351},
{"learn":[0.6756604064],"iteration":13,"passed_time":0.04633594149,"remaining_time":0.7810915852},
{"learn":[0.674822513],"iteration":14,"passed_time":0.04893656613,"remaining_time":0.7666728693},
{"learn":[0.6742283542],"iteration":15,"passed_time":0.05151002349,"remaining_time":0.7533340936},
{"learn":[0.673475594],"iteration":16,"passed_time":0.05415927661,"remaining_time":0.7423006735},
{"learn":[0.6726047524],"iteration":17,"passed_time":0.05674811161,"remaining_time":0.7314201052},
{"learn":[0.6720633926],"iteration":18,"passed_time":0.05933392654,"remaining_time":0.7213756332},
{"learn":[0.6714506792],"iteration":19,"passed_time":0.06201173001,"remaining_time":0.7131348951},
{"learn":[0.6709224168],"iteration":20,"passed_time":0.06462438815,"remaining_time":0.704713566},
{"learn":[0.6703910847],"iteration":21,"passed_time":0.06730904691,"remaining_time":0.6975664862},
{"learn":[0.6698822638],"iteration":22,"passed_time":0.06988061005,"remaining_time":0.6896912383},
{"learn":[0.6691856451],"iteration":23,"passed_time":0.07244465976,"remaining_time":0.6821872128},
{"learn":[0.6687703479],"iteration":24,"passed_time":0.07505184737,"remaining_time":0.6754666264},
{"learn":[0.668429133],"iteration":25,"passed_time":0.07761128555,"remaining_time":0.6686510755},
{"learn":[0.6679624694],"iteration":26,"passed_time":0.08020353066,"remaining_time":0.6624217532},
{"learn":[0.6674624483],"iteration":27,"passed_time":0.08283778656,"remaining_time":0.6567853078},
{"learn":[0.666875725],"iteration":28,"passed_time":0.085414079,"remaining_time":0.6509141883},
{"learn":[0.6665911974],"iteration":29,"passed_time":0.08800518073,"remaining_time":0.6453713254},
{"learn":[0.6662651263],"iteration":30,"passed_time":0.09061477955,"remaining_time":0.6401495717},
{"learn":[0.6659534488],"iteration":31,"passed_time":0.09316032048,"remaining_time":0.6346546832},
{"learn":[0.6657337942],"iteration":32,"passed_time":0.09572153887,"remaining_time":0.6294416344},
{"learn":[0.6652131038],"iteration":33,"passed_time":0.09834089446,"remaining_time":0.6247539177},
{"learn":[0.6649135687],"iteration":34,"passed_time":0.1009118195,"remaining_time":0.6198868913},
{"learn":[0.664583814],"iteration":35,"passed_time":0.1034081131,"remaining_time":0.6147037833},
{"learn":[0.6642132663],"iteration":36,"passed_time":0.1059211289,"remaining_time":0.6097621747},
{"learn":[0.6638372614],"iteration":37,"passed_time":0.108448334,"remaining_time":0.6050275474},
{"learn":[0.663593936],"iteration":38,"passed_time":0.1109915748,"remaining_time":0.6004928788},
{"learn":[0.663415279],"iteration":39,"passed_time":0.1134716096,"remaining_time":0.5957259502},
{"learn":[0.6633408557],"iteration":40,"passed_time":0.1159402765,"remaining_time":0.591012629},
{"learn":[0.6630921413],"iteration":41,"passed_time":0.1184307822,"remaining_time":0.5865143497},
{"learn":[0.6628105469],"iteration":42,"passed_time":0.1210945393,"remaining_time":0.5829434798},
{"learn":[0.6623992062],"iteration":43,"passed_time":0.1236073848,"remaining_time":0.5787073015},
{"learn":[0.6621252519],"iteration":44,"passed_time":0.1261379247,"remaining_time":0.5746283238},
{"learn":[0.6619325426],"iteration":45,"passed_time":0.1287765483,"remaining_time":0.5710959968},
{"learn":[0.6617256444],"iteration":46,"passed_time":0.1313031044,"remaining_time":0.5671176636},
{"learn":[0.661512675],"iteration":47,"passed_time":0.1338384626,"remaining_time":0.5632368634},
{"learn":[0.6613688763],"iteration":48,"passed_time":0.136302394,"remaining_time":0.5591179834},
{"learn":[0.6610097206],"iteration":49,"passed_time":0.1389663127,"remaining_time":0.5558652508},
{"learn":[0.6608466169],"iteration":50,"passed_time":0.1415555411,"remaining_time":0.5523441701},
{"learn":[0.6606668003],"iteration":51,"passed_time":0.1440291073,"remaining_time":0.5484185239},
{"learn":[0.660408331],"iteration":52,"passed_time":0.1465439973,"remaining_time":0.5447012731},
{"learn":[0.6602487745],"iteration":53,"passed_time":0.1491022746,"remaining_time":0.5411860337},
{"learn":[0.6601150717],"iteration":54,"passed_time":0.1516232369,"remaining_time":0.5375732946},
{"learn":[0.6599762528],"iteration":55,"passed_time":0.1541571235,"remaining_time":0.5340443208},
{"learn":[0.6598183334],"iteration":56,"passed_time":0.1566475473,"remaining_time":0.5304030989},
{"learn":[0.6596590497],"iteration":57,"passed_time":0.159213523,"remaining_time":0.5270516624},
{"learn":[0.6594640211],"iteration":58,"passed_time":0.1617263739,"remaining_time":0.5235548715},
{"learn":[0.6593500326],"iteration":59,"passed_time":0.1643109574,"remaining_time":0.5203180317},
{"learn":[0.6592402054],"iteration":60,"passed_time":0.1668369747,"remaining_time":0.5169211185},
{"learn":[0.6591417019],"iteration":61,"passed_time":0.1695127541,"remaining_time":0.5140064157},
{"learn":[0.6590736908],"iteration":62,"passed_time":0.1721841934,"remaining_time":0.5110864153},
{"learn":[0.6589903312],"iteration":63,"passed_time":0.1747844317,"remaining_time":0.5079672547},
{"learn":[0.6588265453],"iteration":64,"passed_time":0.1775562299,"remaining_time":0.5053523466},
{"learn":[0.6586755158],"iteration":65,"passed_time":0.1802709954,"remaining_time":0.5025736841},
{"learn":[0.6584865583],"iteration":66,"passed_time":0.1828721303,"remaining_time":0.4994865649},
{"learn":[0.658424482],"iteration":67,"passed_time":0.1855775654,"remaining_time":0.4966928957},
{"learn":[0.658221745],"iteration":68,"passed_time":0.1881990257,"remaining_time":0.4936815022},
{"learn":[0.6580887926],"iteration":69,"passed_time":0.1908411913,"remaining_time":0.490734492},
{"learn":[0.6578818261],"iteration":70,"passed_time":0.1934628011,"remaining_time":0.4877442451},
{"learn":[0.6577724081],"iteration":71,"passed_time":0.1961704378,"remaining_time":0.4849769157},
{"learn":[0.6576672877],"iteration":72,"passed_time":0.1988528081,"remaining_time":0.4821499594},
{"learn":[0.6576129881],"iteration":73,"passed_time":0.2016654006,"remaining_time":0.4796366285},
{"learn":[0.6575283324],"iteration":74,"passed_time":0.2043658062,"remaining_time":0.4768535477},
{"learn":[0.6574132525],"iteration":75,"passed_time":0.2070678086,"remaining_time":0.4740762987},
{"learn":[0.6573338494],"iteration":76,"passed_time":0.2098122557,"remaining_time":0.4713963668},
{"learn":[0.6571966676],"iteration":77,"passed_time":0.2125021478,"remaining_time":0.4685944799},
{"learn":[0.6570318585],"iteration":78,"passed_time":0.2155577274,"remaining_time":0.4665869795},
{"learn":[0.6568631611],"iteration":79,"passed_time":0.2181159374,"remaining_time":0.4634963669},
{"learn":[0.656729663],"iteration":80,"passed_time":0.2206587531,"remaining_time":0.4603867811},
{"learn":[0.6565870239],"iteration":81,"passed_time":0.223219766,"remaining_time":0.4573283011},
{"learn":[0.6564173033],"iteration":82,"passed_time":0.2259013295,"remaining_time":0.4545243618},
{"learn":[0.6563404242],"iteration":83,"passed_time":0.22849487,"remaining_time":0.451549386},
{"learn":[0.6562572692],"iteration":84,"passed_time":0.2310093993,"remaining_time":0.4484300103},
{"learn":[0.6561692028],"iteration":85,"passed_time":0.2335213377,"remaining_time":0.4453197603},
{"learn":[0.6560420487],"iteration":86,"passed_time":0.2360217054,"remaining_time":0.442201586},
{"learn":[0.6559663293],"iteration":87,"passed_time":0.2384299692,"remaining_time":0.4389278979},
{"learn":[0.655834673],"iteration":88,"passed_time":0.2409709508,"remaining_time":0.4359137425},
{"learn":[0.6557026074],"iteration":89,"passed_time":0.2435471694,"remaining_time":0.4329727455},
{"learn":[0.6556106526],"iteration":90,"passed_time":0.2460988932,"remaining_time":0.4299969673},
{"learn":[0.6555100345],"iteration":91,"passed_time":0.2486023261,"remaining_time":0.426947473},
{"learn":[0.6554462528],"iteration":92,"passed_time":0.2510515296,"remaining_time":0.4238181736},
{"learn":[0.6553261932],"iteration":93,"passed_time":0.2534650686,"remaining_time":0.4206441563},
{"learn":[0.6552482226],"iteration":94,"passed_time":0.2560796076,"remaining_time":0.4178140966},
{"learn":[0.6550733858],"iteration":95,"passed_time":0.2586150301,"remaining_time":0.4148616108},
{"learn":[0.6550038058],"iteration":96,"passed_time":0.2610738935,"remaining_time":0.411796966},
{"learn":[0.654897935],"iteration":97,"passed_time":0.2636311748,"remaining_time":0.4088973323},
{"learn":[0.6548027741],"iteration":98,"passed_time":0.2661256342,"remaining_time":0.4059087957},
{"learn":[0.6547368777],"iteration":99,"passed_time":0.2687246219,"remaining_time":0.4030869328},
{"learn":[0.6545943069],"iteration":100,"passed_time":0.2713409566,"remaining_time":0.4002950745},
{"learn":[0.6544872765],"iteration":101,"passed_time":0.2738060923,"remaining_time":0.3972872712},
{"learn":[0.6543019344],"iteration":102,"passed_time":0.2764787142,"remaining_time":0.3945861261},
{"learn":[0.654247089],"iteration":103,"passed_time":0.2791106704,"remaining_time":0.3918284411},
{"learn":[0.6540539704],"iteration":104,"passed_time":0.2816555724,"remaining_time":0.3889529333},
{"learn":[0.6539648124],"iteration":105,"passed_time":0.2841410719,"remaining_time":0.3860029656},
{"learn":[0.6539092166],"iteration":106,"passed_time":0.2866283654,"remaining_time":0.3830640771},
{"learn":[0.6538689694],"iteration":107,"passed_time":0.2892779643,"remaining_time":0.380346953},
{"learn":[0.6538004808],"iteration":108,"passed_time":0.291776553,"remaining_time":0.3774357245},
{"learn":[0.6537032734],"iteration":109,"passed_time":0.2943701686,"remaining_time":0.3746529419},
{"learn":[0.6536557271],"iteration":110,"passed_time":0.2968598023,"remaining_time":0.3717433561},
{"learn":[0.6536077032],"iteration":111,"passed_time":0.2993386937,"remaining_time":0.3688280334},
{"learn":[0.6535214786],"iteration":112,"passed_time":0.3019408785,"remaining_time":0.3660699147},
{"learn":[0.653449511],"iteration":113,"passed_time":0.3045144812,"remaining_time":0.3632804337},
{"learn":[0.6533556462],"iteration":114,"passed_time":0.3070581271,"remaining_time":0.3604595405},
{"learn":[0.6532596667],"iteration":115,"passed_time":0.3096655652,"remaining_time":0.3577171185},
{"learn":[0.6531414489],"iteration":116,"passed_time":0.3121654769,"remaining_time":0.3548547729},
{"learn":[0.653070641],"iteration":117,"passed_time":0.3147025865,"remaining_time":0.3520401815},
{"learn":[0.6529995603],"iteration":118,"passed_time":0.3172027036,"remaining_time":0.3491895309},
{"learn":[0.6529208394],"iteration":119,"passed_time":0.3198038978,"remaining_time":0.3464542227},
{"learn":[0.6528217902],"iteration":120,"passed_time":0.322378441,"remaining_time":0.343692718},
{"learn":[0.65276292],"iteration":121,"passed_time":0.3251401366,"remaining_time":0.3411306351},
{"learn":[0.6526852906],"iteration":122,"passed_time":0.3275932154,"remaining_time":0.3382466533},
{"learn":[0.6526071836],"iteration":123,"passed_time":0.3301892799,"remaining_time":0.3355149134},
{"learn":[0.6524702747],"iteration":124,"passed_time":0.3326899465,"remaining_time":0.3326899465},
{"learn":[0.6524236151],"iteration":125,"passed_time":0.3351999624,"remaining_time":0.329879328},
{"learn":[0.6523339115],"iteration":126,"passed_time":0.3377451199,"remaining_time":0.3271074784},
{"learn":[0.6522510294],"iteration":127,"passed_time":0.3403704681,"remaining_time":0.3244156024},
{"learn":[0.652167397],"iteration":128,"passed_time":0.3429328507,"remaining_time":0.3216656972},
{"learn":[0.6520922915],"iteration":129,"passed_time":0.345409736,"remaining_time":0.3188397563},
{"learn":[0.6519770752],"iteration":130,"passed_time":0.347984092,"remaining_time":0.3161076866},
{"learn":[0.6518862801],"iteration":131,"passed_time":0.3513036187,"remaining_time":0.314044144},
{"learn":[0.6518289789],"iteration":132,"passed_time":0.353915029,"remaining_time":0.3113387849},
{"learn":[0.6517652654],"iteration":133,"passed_time":0.3565656636,"remaining_time":0.3086687834},
{"learn":[0.6516892049],"iteration":134,"passed_time":0.359062961,"remaining_time":0.3058684483},
{"learn":[0.6516132126],"iteration":135,"passed_time":0.3617551399,"remaining_time":0.3032359261},
{"learn":[0.6514768494],"iteration":136,"passed_time":0.3643283868,"remaining_time":0.3005044358},
{"learn":[0.6513693415],"iteration":137,"passed_time":0.3668080199,"remaining_time":0.2976992625},
{"learn":[0.6513038544],"iteration":138,"passed_time":0.3693940252,"remaining_time":0.294983718},
{"learn":[0.6512204948],"iteration":139,"passed_time":0.3719804649,"remaining_time":0.2922703653},
{"learn":[0.651105756],"iteration":140,"passed_time":0.3745671067,"remaining_time":0.289558969},
{"learn":[0.6510468859],"iteration":141,"passed_time":0.3771633983,"remaining_time":0.2868566691},
{"learn":[0.6510049332],"iteration":142,"passed_time":0.3800077115,"remaining_time":0.2843414345},
{"learn":[0.6509473592],"iteration":143,"passed_time":0.3825338166,"remaining_time":0.2815873928},
{"learn":[0.6508922409],"iteration":144,"passed_time":0.384973402,"remaining_time":0.2787738428},
{"learn":[0.6507846647],"iteration":145,"passed_time":0.3873544719,"remaining_time":0.2759237334},
{"learn":[0.6507688387],"iteration":146,"passed_time":0.3898410721,"remaining_time":0.2731539485},
{"learn":[0.6507137204],"iteration":147,"passed_time":0.3923204279,"remaining_time":0.2703829976},
{"learn":[0.6506271547],"iteration":148,"passed_time":0.3947969156,"remaining_time":0.2676140166},
{"learn":[0.6505648737],"iteration":149,"passed_time":0.3973829928,"remaining_time":0.2649219952},
{"learn":[0.6505075043],"iteration":150,"passed_time":0.3998618425,"remaining_time":0.2621610755},
{"learn":[0.6503978135],"iteration":151,"passed_time":0.4022791432,"remaining_time":0.2593641844},
{"learn":[0.6503094059],"iteration":152,"passed_time":0.4048825891,"remaining_time":0.2566902689},
{"learn":[0.6502104932],"iteration":153,"passed_time":0.4074619513,"remaining_time":0.2540022554},
{"learn":[0.6501563299],"iteration":154,"passed_time":0.4099447548,"remaining_time":0.2512564626},
{"learn":[0.6501434372],"iteration":155,"passed_time":0.4123436962,"remaining_time":0.2484635092},
{"learn":[0.6500793144],"iteration":156,"passed_time":0.4151425246,"remaining_time":0.2459124509},
{"learn":[0.6500063236],"iteration":157,"passed_time":0.4177414755,"remaining_time":0.2432418718},
{"learn":[0.6498494275],"iteration":158,"passed_time":0.4202154576,"remaining_time":0.2405006707},
{"learn":[0.6497756863],"iteration":159,"passed_time":0.422676668,"remaining_time":0.2377556257},
{"learn":[0.6497320283],"iteration":160,"passed_time":0.4253182005,"remaining_time":0.2351137879},
{"learn":[0.6496869377],"iteration":161,"passed_time":0.427774266,"remaining_time":0.2323712062},
{"learn":[0.6496009177],"iteration":162,"passed_time":0.4301968151,"remaining_time":0.229614251},
{"learn":[0.6495119644],"iteration":163,"passed_time":0.4326953436,"remaining_time":0.2269012168},
{"learn":[0.6493959977],"iteration":164,"passed_time":0.4353408534,"remaining_time":0.2242665002},
{"learn":[0.6493658464],"iteration":165,"passed_time":0.4377256299,"remaining_time":0.2214997163},
{"learn":[0.6492892402],"iteration":166,"passed_time":0.440566629,"remaining_time":0.2189642528},
{"learn":[0.649219933],"iteration":167,"passed_time":0.4430557098,"remaining_time":0.2162533822},
{"learn":[0.6491910778],"iteration":168,"passed_time":0.4455696678,"remaining_time":0.2135570597},
{"learn":[0.6491354138],"iteration":169,"passed_time":0.4480057738,"remaining_time":0.2108262465},
{"learn":[0.6490837745],"iteration":170,"passed_time":0.4504533954,"remaining_time":0.2081042002},
{"learn":[0.6489740154],"iteration":171,"passed_time":0.4528867302,"remaining_time":0.205378866},
{"learn":[0.6489378611],"iteration":172,"passed_time":0.4552753169,"remaining_time":0.2026369907},
{"learn":[0.6488685539],"iteration":173,"passed_time":0.4578320402,"remaining_time":0.1999726153},
{"learn":[0.6488258509],"iteration":174,"passed_time":0.4603313756,"remaining_time":0.1972848753},
{"learn":[0.6487914702],"iteration":175,"passed_time":0.4627610405,"remaining_time":0.1945699829},
{"learn":[0.6487625467],"iteration":176,"passed_time":0.4651898252,"remaining_time":0.1918579505},
{"learn":[0.6487410588],"iteration":177,"passed_time":0.4678683218,"remaining_time":0.1892501077},
{"learn":[0.6486997201],"iteration":178,"passed_time":0.4703851328,"remaining_time":0.1865773432},
{"learn":[0.6486813701],"iteration":179,"passed_time":0.4728415274,"remaining_time":0.1838828162},
{"learn":[0.6486183388],"iteration":180,"passed_time":0.4752923412,"remaining_time":0.1811887931},
{"learn":[0.6485777504],"iteration":181,"passed_time":0.4778614138,"remaining_time":0.1785416271},
{"learn":[0.64855865],"iteration":182,"passed_time":0.4802808793,"remaining_time":0.1758405405},
{"learn":[0.6485018263],"iteration":183,"passed_time":0.4827622947,"remaining_time":0.1731647361},
{"learn":[0.6484838856],"iteration":184,"passed_time":0.4851617973,"remaining_time":0.1704622531},
{"learn":[0.6484625341],"iteration":185,"passed_time":0.4876253061,"remaining_time":0.1677850516},
{"learn":[0.6484240604],"iteration":186,"passed_time":0.4900577856,"remaining_time":0.1650996818},
{"learn":[0.6483687375],"iteration":187,"passed_time":0.4925709218,"remaining_time":0.1624436019},
{"learn":[0.6483376311],"iteration":188,"passed_time":0.4950018946,"remaining_time":0.1597625163},
{"learn":[0.6482610249],"iteration":189,"passed_time":0.4975469252,"remaining_time":0.1571200817},
{"learn":[0.6482019501],"iteration":190,"passed_time":0.5000918657,"remaining_time":0.1544786391},
{"learn":[0.6481392599],"iteration":191,"passed_time":0.5024252224,"remaining_time":0.1517742859},
{"learn":[0.6480753418],"iteration":192,"passed_time":0.5049832203,"remaining_time":0.1491401221},
{"learn":[0.6479727454],"iteration":193,"passed_time":0.5076291594,"remaining_time":0.1465321285},
{"learn":[0.6479468234],"iteration":194,"passed_time":0.5101695045,"remaining_time":0.1438939628},
{"learn":[0.6479258812],"iteration":195,"passed_time":0.5126118695,"remaining_time":0.1412298008},
{"learn":[0.6478758791],"iteration":196,"passed_time":0.5152050224,"remaining_time":0.1386084578},
{"learn":[0.6477791492],"iteration":197,"passed_time":0.5177733083,"remaining_time":0.1359808688},
{"learn":[0.6477460646],"iteration":198,"passed_time":0.5203784914,"remaining_time":0.133363332},
{"learn":[0.6476821465],"iteration":199,"passed_time":0.5228025071,"remaining_time":0.1307006268},
{"learn":[0.6475663844],"iteration":200,"passed_time":0.5252419321,"remaining_time":0.1280440531},
{"learn":[0.6475388935],"iteration":201,"passed_time":0.5276181061,"remaining_time":0.1253745995},
{"learn":[0.6475125623],"iteration":202,"passed_time":0.5302123114,"remaining_time":0.1227585154},
{"learn":[0.6474804327],"iteration":203,"passed_time":0.5327317315,"remaining_time":0.1201257826},
{"learn":[0.6474597633],"iteration":204,"passed_time":0.5352075043,"remaining_time":0.1174845741},
{"learn":[0.6473784502],"iteration":205,"passed_time":0.5376870956,"remaining_time":0.1148457874},
{"learn":[0.647362897],"iteration":206,"passed_time":0.5402029796,"remaining_time":0.1122160779},
{"learn":[0.647328721],"iteration":207,"passed_time":0.5426554019,"remaining_time":0.1095746485},
{"learn":[0.6472944767],"iteration":208,"passed_time":0.5449938133,"remaining_time":0.1069126619},
{"learn":[0.6472638478],"iteration":209,"passed_time":0.5474344895,"remaining_time":0.1042732361},
{"learn":[0.6472330825],"iteration":210,"passed_time":0.5499246777,"remaining_time":0.1016448456},
{"learn":[0.6471471308],"iteration":211,"passed_time":0.5524729606,"remaining_time":0.09902817219},
{"learn":[0.6471022448],"iteration":212,"passed_time":0.5549838518,"remaining_time":0.09640564561},
{"learn":[0.6470900342],"iteration":213,"passed_time":0.5575961758,"remaining_time":0.09380122584},
{"learn":[0.647029868],"iteration":214,"passed_time":0.5601052028,"remaining_time":0.09117991673},
{"learn":[0.6469839588],"iteration":215,"passed_time":0.5625930976,"remaining_time":0.08855632092},
{"learn":[0.6468838864],"iteration":216,"passed_time":0.5650880081,"remaining_time":0.08593504271},
{"learn":[0.6468557815],"iteration":217,"passed_time":0.567547092,"remaining_time":0.08330966488},
{"learn":[0.6467967749],"iteration":218,"passed_time":0.5700213731,"remaining_time":0.08068795693},
{"learn":[0.6467550951],"iteration":219,"passed_time":0.572619437,"remaining_time":0.07808446869},
{"learn":[0.6467071395],"iteration":220,"passed_time":0.5751570394,"remaining_time":0.07547309567},
{"learn":[0.6466593885],"iteration":221,"passed_time":0.5775728201,"remaining_time":0.07284702235},
{"learn":[0.6466284186],"iteration":222,"passed_time":0.580097507,"remaining_time":0.07023602102},
{"learn":[0.6466203009],"iteration":223,"passed_time":0.5827112559,"remaining_time":0.06763612791},
{"learn":[0.6465770522],"iteration":224,"passed_time":0.5852041285,"remaining_time":0.06502268094},
{"learn":[0.6465380328],"iteration":225,"passed_time":0.5876955595,"remaining_time":0.06241014792},
{"learn":[0.6464492159],"iteration":226,"passed_time":0.5902761261,"remaining_time":0.05980771322},
{"learn":[0.6464190646],"iteration":227,"passed_time":0.592826056,"remaining_time":0.05720251417},
{"learn":[0.6463785445],"iteration":228,"passed_time":0.595324785,"remaining_time":0.05459310255},
{"learn":[0.6463513264],"iteration":229,"passed_time":0.5978725083,"remaining_time":0.05198891376},
{"learn":[0.6463275873],"iteration":230,"passed_time":0.6003070407,"remaining_time":0.04937590378},
{"learn":[0.6462817464],"iteration":231,"passed_time":0.6029469497,"remaining_time":0.04678036678},
{"learn":[0.6462326993],"iteration":232,"passed_time":0.6052857803,"remaining_time":0.04416248182},
{"learn":[0.6462043216],"iteration":233,"passed_time":0.6077221702,"remaining_time":0.04155365267},
{"learn":[0.6461917699],"iteration":234,"passed_time":0.6101973584,"remaining_time":0.03894876756},
{"learn":[0.6461664619],"iteration":235,"passed_time":0.6126283396,"remaining_time":0.03634235913},
{"learn":[0.6461541148],"iteration":236,"passed_time":0.6151306048,"remaining_time":0.03374134119},
{"learn":[0.6461220534],"iteration":237,"passed_time":0.61758727,"remaining_time":0.03113885395},
{"learn":[0.6461084103],"iteration":238,"passed_time":0.6200810563,"remaining_time":0.02853929548},
{"learn":[0.6460698002],"iteration":239,"passed_time":0.6225388841,"remaining_time":0.02593912017},
{"learn":[0.6460198663],"iteration":240,"passed_time":0.6251421245,"remaining_time":0.02334555652},
{"learn":[0.6459890328],"iteration":241,"passed_time":0.6275637215,"remaining_time":0.02074590815},
{"learn":[0.6459622241],"iteration":242,"passed_time":0.6300106649,"remaining_time":0.01814845537},
{"learn":[0.6459120173],"iteration":243,"passed_time":0.6323905204,"remaining_time":0.01555058657},
{"learn":[0.6459086065],"iteration":244,"passed_time":0.6350266576,"remaining_time":0.01295972771},
{"learn":[0.6458764769],"iteration":245,"passed_time":0.6374246369,"remaining_time":0.01036462824},
{"learn":[0.6457945499],"iteration":246,"passed_time":0.6400266062,"remaining_time":0.007773602504},
{"learn":[0.6457255156],"iteration":247,"passed_time":0.6424646648,"remaining_time":0.005181166652},
{"learn":[0.6456875194],"iteration":248,"passed_time":0.6450885296,"remaining_time":0.002590716987},
{"learn":[0.6456438614],"iteration":249,"passed_time":0.6474966281,"remaining_time":0}
]}